kivy_ios/__init__.py
kivy_ios/context_managers.py
kivy_ios/toolchain.py
kivy_ios/recipes/__init__.py
kivy_ios/recipes/hostpython.py
kivy_ios/recipes/python.py
kivy_ios/recipes/audiostream/__init__.py
kivy_ios/recipes/click/__init__.py
kivy_ios/recipes/curly/__init__.py
kivy_ios/recipes/cymunk/__init__.py
kivy_ios/recipes/ffmpeg/__init__.py
kivy_ios/recipes/ffpyplayer/__init__.py
kivy_ios/recipes/ffpyplayer/misc-visibility.patch
kivy_ios/recipes/flask/__init__.py
kivy_ios/recipes/freetype/__init__.py
kivy_ios/recipes/hostopenssl/__init__.py
kivy_ios/recipes/hostpython3/ModulesSetup
kivy_ios/recipes/hostpython3/__init__.py
kivy_ios/recipes/hostpython3/allow-cflags-override.patch
kivy_ios/recipes/hostpython3/disable_sysconfig_cflags.patch
kivy_ios/recipes/ios/__init__.py
kivy_ios/recipes/ios/src/ios.pyx
kivy_ios/recipes/ios/src/ios_browser.m
kivy_ios/recipes/ios/src/ios_filechooser.m
kivy_ios/recipes/ios/src/ios_mail.m
kivy_ios/recipes/ios/src/ios_utils.m
kivy_ios/recipes/ios/src/ios_wrapper.h
kivy_ios/recipes/ios/src/setup.py
kivy_ios/recipes/itsdangerous/__init__.py
kivy_ios/recipes/jinja2/__init__.py
kivy_ios/recipes/kivent_core/__init__.py
kivy_ios/recipes/kivy/__init__.py
kivy_ios/recipes/kiwisolver/__init__.py
kivy_ios/recipes/libcurl/__init__.py
kivy_ios/recipes/libffi/__init__.py
kivy_ios/recipes/libffi/enable-tramp-build.patch
kivy_ios/recipes/libjpeg/__init__.py
kivy_ios/recipes/libpng/__init__.py
kivy_ios/recipes/libzbar/__init__.py
kivy_ios/recipes/libzbar/werror.patch
kivy_ios/recipes/markupsafe/__init__.py
kivy_ios/recipes/materialyoucolor/__init__.py
kivy_ios/recipes/materialyoucolor/fix_cert.patch
kivy_ios/recipes/matplotlib/__init__.py
kivy_ios/recipes/matplotlib/_tri.cpp.patch
kivy_ios/recipes/matplotlib/_tri.h.patch
kivy_ios/recipes/matplotlib/_tri_wrapper.cpp.patch
kivy_ios/recipes/matplotlib/libfreetype.pc.template
kivy_ios/recipes/matplotlib/mplsetup.cfg
kivy_ios/recipes/matplotlib/setup.py.patch
kivy_ios/recipes/matplotlib/setupext.py.patch
kivy_ios-2024.3.17.dist-info/LICENSE
kivy_ios-2024.3.17.dist-info/METADATA
kivy_ios-2024.3.17.dist-info/WHEEL
kivy_ios-2024.3.17.dist-info/entry_points.txt
kivy_ios-2024.3.17.dist-info/top_level.txt
kivy_ios-2024.3.17.dist-info/RECORD
