Metadata-Version: 2.1
Name: kivy-ios
Version: 2024.3.17
Summary: A toolchain to compile the necessary libraries for iOS to run Kivy applications.
Home-page: https://github.com/kivy/kivy-ios
Author: The Kivy team
Author-email: kivy-dev@googlegroups.com
License: MIT License
Project-URL: Source, https://github.com/kivy/kivy-ios
Project-URL: Bug Reports, https://github.com/kivy/kivy-ios/issues
Classifier: Development Status :: 5 - Production/Stable
Classifier: Intended Audience :: Developers
Classifier: Topic :: Software Development :: Build Tools
Classifier: Programming Language :: Python :: 3
Classifier: Programming Language :: Python :: 3.6
Classifier: Programming Language :: Python :: 3.7
Classifier: Programming Language :: Python :: 3.8
Classifier: Programming Language :: Python :: 3.9
Classifier: Programming Language :: Python :: 3.10
Classifier: Programming Language :: Python :: 3.11
Classifier: Programming Language :: Python :: 3.12
Classifier: Operating System :: MacOS :: MacOS X
Classifier: Operating System :: iOS
License-File: LICENSE
Requires-Dist: Cython==0.29.36
Requires-Dist: cookiecutter
Requires-Dist: pbxproj
Requires-Dist: Pillow
Requires-Dist: sh
